lite_camera-2.0.8.dist-info/licenses/LICENSE
litecam/__init__.py
litecam/litecam.cp312-win_amd64.pyd
lite_camera-2.0.8.dist-info/METADATA
lite_camera-2.0.8.dist-info/WHEEL
lite_camera-2.0.8.dist-info/top_level.txt
lite_camera-2.0.8.dist-info/RECORD
